{
  "pune": [
    "Baner",
    "Balewadi",
    "Aundh",
    "Kothrud",
    "Karve Nagar",
    "Warje",
    "Sinhagad Road",
    "Swargate",
    "Shivajinagar",
    "Camp",
    "Koregaon Park",
    "Kalyani Nagar",
    "Viman Nagar",
    "Kharadi",
    "Hadapsar",
    "Magarpatta",
    "Katraj",
    "Bavdhan",
    "Pashan",
    "Sus",
    "Yerwada",
    "Dhanori",
    "Lohegaon",
    "Wagholi"
  ],
  "pcmc": [
    "Hinjawadi",
    "Wakad",
    "Pimple Saudagar",
    "Pimpri",
    "Chinchwad",
    "Nigdi",
    "Bhosari",
    "Akurdi",
    "Ravet",
    "Moshi",
    "Dapodi",
    "Sangvi"
  ],
  "nearby": [
    "Chakan",
    "Talegaon",
    "Alandi",
    "Saswad",
    "Ranjangaon",
    "Fursungi",
    "Uruli Devachi",
    "Khed Shivapur"
  ],
  "aliases": {
    "KP": "Koregaon Park",
    "SB Road": "Senapati Bapat Road",
    "FC Road": "Fergusson College Road",
    "JM Road": "Jangli Maharaj Road",
    "PCMC": "Pimpri-Chinchwad",
    "Mumbai Pune Expressway": "Mumbai-Pune Expressway"
  }
}
