{
  "generatedAt": "2026-07-19T18:57:31.636Z",
  "source": "Open-Meteo",
  "regions": {
    "talegaon": {
      "label": "Talegaon Dabhade",
      "error": true,
      "message": "Open-Meteo failed for talegaon: HTTP 429",
      "updatedAt": "2026-07-19T18:57:31.551Z"
    },
    "pune": {
      "label": "Pune City (PMC)",
      "temp": 23.2,
      "humidity": 88,
      "rain": 0,
      "wind": 11.2,
      "gust": 27.4,
      "code": 3,
      "rainChance": 65,
      "visibility": 19,
      "next6hRainMm": 0,
      "source": "Open-Meteo",
      "updatedAt": "2026-07-19T18:57:31.565Z"
    },
    "alandi": {
      "label": "Alandi Area",
      "temp": 23.2,
      "humidity": 89,
      "rain": 0,
      "wind": 11.1,
      "gust": 22.7,
      "code": 3,
      "rainChance": 66,
      "visibility": 19,
      "next6hRainMm": 0.3,
      "source": "Open-Meteo",
      "updatedAt": "2026-07-19T18:57:31.566Z"
    },
    "chakan": {
      "label": "Chakan Industrial Cluster",
      "temp": 22.8,
      "humidity": 92,
      "rain": 0,
      "wind": 11.9,
      "gust": 22.3,
      "code": 3,
      "rainChance": 68,
      "visibility": 19,
      "next6hRainMm": 0.3,
      "source": "Open-Meteo",
      "updatedAt": "2026-07-19T18:57:31.575Z"
    },
    "pcmc": {
      "label": "Pimpri-Chinchwad (PCMC)",
      "temp": 23.2,
      "humidity": 89,
      "rain": 0,
      "wind": 11,
      "gust": 24.1,
      "code": 3,
      "rainChance": 68,
      "visibility": 18,
      "next6hRainMm": 0.2,
      "source": "Open-Meteo",
      "updatedAt": "2026-07-19T18:57:31.583Z"
    },
    "ranjangaon": {
      "label": "Ranjangaon Zone",
      "temp": 23,
      "humidity": 89,
      "rain": 0,
      "wind": 14,
      "gust": 24.5,
      "code": 3,
      "rainChance": 61,
      "visibility": 19,
      "next6hRainMm": 0.1,
      "source": "Open-Meteo",
      "updatedAt": "2026-07-19T18:57:31.586Z"
    },
    "saswad": {
      "label": "Saswad Region",
      "temp": 20.5,
      "humidity": 98,
      "rain": 0,
      "wind": 13.9,
      "gust": 36.4,
      "code": 3,
      "rainChance": 71,
      "visibility": 12,
      "next6hRainMm": 0.2,
      "source": "Open-Meteo",
      "updatedAt": "2026-07-19T18:57:31.587Z"
    },
    "khed": {
      "label": "Khed Shivapur / Ghats",
      "temp": 20.8,
      "humidity": 98,
      "rain": 0,
      "wind": 10.7,
      "gust": 24.5,
      "code": 3,
      "rainChance": 90,
      "visibility": 11,
      "next6hRainMm": 0,
      "source": "Open-Meteo",
      "updatedAt": "2026-07-19T18:57:31.588Z"
    },
    "fursungi": {
      "label": "Fursungi / Uruli",
      "temp": 23.5,
      "humidity": 87,
      "rain": 0,
      "wind": 10.5,
      "gust": 25.2,
      "code": 3,
      "rainChance": 59,
      "visibility": 21,
      "next6hRainMm": 0,
      "source": "Open-Meteo",
      "updatedAt": "2026-07-19T18:57:31.636Z"
    }
  }
}