{
  "generatedAt": "2026-07-15T17:44:44.121Z",
  "source": "Open-Meteo",
  "regions": {
    "pune": {
      "label": "Pune City (PMC)",
      "temp": 23.3,
      "humidity": 87,
      "rain": 0,
      "wind": 9,
      "gust": 23.4,
      "code": 2,
      "rainChance": 0,
      "visibility": 21,
      "next6hRainMm": 0,
      "source": "Open-Meteo",
      "updatedAt": "2026-07-15T17:44:44.101Z"
    },
    "pcmc": {
      "label": "Pimpri-Chinchwad (PCMC)",
      "temp": 23.1,
      "humidity": 89,
      "rain": 0,
      "wind": 7.2,
      "gust": 19.1,
      "code": 1,
      "rainChance": 0,
      "visibility": 20,
      "next6hRainMm": 0,
      "source": "Open-Meteo",
      "updatedAt": "2026-07-15T17:44:44.103Z"
    },
    "alandi": {
      "label": "Alandi Area",
      "temp": 23,
      "humidity": 89,
      "rain": 0,
      "wind": 9.4,
      "gust": 18.4,
      "code": 1,
      "rainChance": 0,
      "visibility": 23,
      "next6hRainMm": 0,
      "source": "Open-Meteo",
      "updatedAt": "2026-07-15T17:44:44.105Z"
    },
    "talegaon": {
      "label": "Talegaon Dabhade",
      "temp": 22.5,
      "humidity": 92,
      "rain": 0,
      "wind": 10.9,
      "gust": 20.5,
      "code": 2,
      "rainChance": 0,
      "visibility": 18,
      "next6hRainMm": 0,
      "source": "Open-Meteo",
      "updatedAt": "2026-07-15T17:44:44.112Z"
    },
    "saswad": {
      "label": "Saswad Region",
      "temp": 21.1,
      "humidity": 95,
      "rain": 0,
      "wind": 15.9,
      "gust": 36,
      "code": 2,
      "rainChance": 0,
      "visibility": 12,
      "next6hRainMm": 0,
      "source": "Open-Meteo",
      "updatedAt": "2026-07-15T17:44:44.112Z"
    },
    "chakan": {
      "label": "Chakan Industrial Cluster",
      "temp": 22.6,
      "humidity": 91,
      "rain": 0,
      "wind": 10,
      "gust": 17.3,
      "code": 1,
      "rainChance": 0,
      "visibility": 21,
      "next6hRainMm": 0,
      "source": "Open-Meteo",
      "updatedAt": "2026-07-15T17:44:44.113Z"
    },
    "khed": {
      "label": "Khed Shivapur / Ghats",
      "temp": 21.3,
      "humidity": 95,
      "rain": 0,
      "wind": 12.8,
      "gust": 27.4,
      "code": 3,
      "rainChance": 57,
      "visibility": 11,
      "next6hRainMm": 0,
      "source": "Open-Meteo",
      "updatedAt": "2026-07-15T17:44:44.114Z"
    },
    "ranjangaon": {
      "label": "Ranjangaon Zone",
      "temp": 22.9,
      "humidity": 88,
      "rain": 0,
      "wind": 14.4,
      "gust": 26.3,
      "code": 1,
      "rainChance": 0,
      "visibility": 27,
      "next6hRainMm": 0,
      "source": "Open-Meteo",
      "updatedAt": "2026-07-15T17:44:44.115Z"
    },
    "fursungi": {
      "label": "Fursungi / Uruli",
      "temp": 23.5,
      "humidity": 87,
      "rain": 0,
      "wind": 8.1,
      "gust": 20.2,
      "code": 1,
      "rainChance": 0,
      "visibility": 21,
      "next6hRainMm": 0,
      "source": "Open-Meteo",
      "updatedAt": "2026-07-15T17:44:44.120Z"
    }
  }
}